{
  "project_info": {
    "project_number": "355056649988",
    "project_id": "unievent-2a2fb",
    "storage_bucket": "unievent-2a2fb.appspot.com"
  },
  "client": [
    {
      "client_info": {
        "mobilesdk_app_id": "1:355056649988:android:edd53c509f3f0e1ad73251",
        "android_client_info": {
          "package_name": "com.example.uni"
        }
      },
      "oauth_client": [],
      "api_key": [
        {
          "current_key": "AIzaSyAldoyNM9PMfVFiIlWNadMm8thQ5p4HbVA"
        }
      ],
      "services": {
        "appinvite_service": {
          "other_platform_oauth_client": []
        }
      }
    }
  ],
  "configuration_version": "1"
}